{
    "stops": {
        "Allison Road Classrooms": [
            "ar",
            "arc",
            "all",
            "ali",
        ],
        "Biel Road": [
            "biel",
            "beil",
            "bei",
            "broad",
            "biel road",
            "bielroad",
        ],
        "Bravo Supermarket": [
            "bra",
            "cto",
            "c t",
            "c-t",
        ],
        "Buell Apartments": [
            "bue",
            "bap",
            "bapts",
            "buell",
            "bes",
        ],
        "Busch Campus Center": [
            "bcc",
            "bsc",
            "bus",
            "bush",
            "b",
            "busch",
        ],
        "Busch Suites": [
            "sui",
            "bsu",
            "bs",
            "suites",
            "bsuites",
            "busch suites",
        ],
        "Cabaret Theatre": [
            "cab",
            "cth",
            "jam",
        ],
        "College Hall": [
            "cha",
            "c",
            "dcc",
            "college hall",
            "dou",
        ],
        "Colony House": [
            "colony",
            "colony house",
            "chouse",
            "cho",
        ],
        "Davidson": [
            "dav",
            "dvd",
            "dvdson",
            "dvdsn",
            "david",
            "davidson",
        ],
        "Food Sciences Building": [
            "food",
            "foodsci",
            "foo",
            "fsci",
            "fsb",
            "fsc",
        ],
        "Gibbons": [
            "new",
            "gib",
            "gibb",
            "gbb",
            "gbons",
            "gibbons",
            "new gibbons",
            "newgibbons",
        ],
        "Henderson": [
            "hen",
            "hap",
            "hend",
            "henderson",
            "hapts",
        ],
        "Hill Center": [
            "hil",
            "hill",
            "hill center",
            "ser",
            "h",
            "plh",
            "physics",
            "phy",
        ],
        "Katzenbach": [
            "kat",
            "katz",
            "kac",
            "kba",
            "katzenbach",
        ],
        "Liberty Street": [
            "lty",
            "libty",
            "lbu",
            "lbt",
            "lbr",
            "lib",
        ],
        "Library of Science": [
            "lsm",
            "lib",
            "libofsci",
            "l.s",
        ],
        "Lipman Hall": [
            "lip",
            "lma",
            "lip",
            "lha",
            "lhall",
        ],
        "Livingston Plaza": [
            "beck",
            "bec",
            "lpa",
            "pla",
            "rac",
            "lpl",
            "liv",
        ],
        "Livingston Student Center": [
            "lsc",
            "lcc",
            "livingston",
            "liv",
        ],
        "Nursing School": [
            "nursing",
            "nur",
            "nurse",
            "nsc",
        ],
        "Paterson Street": [
            "pat",
            "bk",
            "bki",
            "burger king",
            "bur",
            "p st",
            "pat",
            "pson",
            "paterson",
            "patterson",
            "pso",
        ],
        "Public Safety Building North": [
            "psb",
            "public",
            "safety",
            "psa",
            "saf",
            "pub",
        ],
        "Public Safety Building South": [
            "psb",
            "public",
            "safety",
            "psa",
            "saf",
            "pub",
        ],
        "Quads": [
            "q",
            "qua",
            "quad",
            "quads",
        ],
        "Red Oak Lane": [
            "pass",
            "pas",
            "roa",
            "roak",
            "red",
            "oak",
            "puddle",
            "pud",
            "red oak",
            "redoak",
            "red oak lane",
        ],
        "Rockoff Hall": [
            "roc",
            "rockoff",
            "rockoff hall",
            "rha",
        ],
        "Rutgers Student Center": [
            "rsc",
            "rut",
            "rsc",
            "col",
            "college ave",
            "bro",
            "brower",
            "rutgers student center",
            "ccc",
            "cac",
            "rcc",
        ],
        "Science Building": [
            "sci",
            "science",
            "science building",
            "sciences building",
            "science buildings",
        ],
        "Scott Hall": [
           "sha",
           "sco",
           "sec",
           "gre",
           "tru",
           "sct",
           "s",
           "mur",
           "murray",
           "scott",
           "grease trucks",
        ],
        "Stadium": [
            "football",
            "stadium",
            "wes",
            "sta",
            "stdium",
        ],
        "Student Activities Center": [
            "sac",
            "frelinghuysen",
            "fre",
            "campbell",
            "cam",
            "student activities center",
            "stu",
            "activities",
            "act",
            "hardenbergh",
            "hard",
            "har",
        ],
        "Train Station": [
           "train",
           "tst",
           "train station",
           "trn",
           "tra",
        ],
        "Visitor Center": [
            "vis",
            "visitor center",
            "visitor",
            "vsn",
            "lot48",
            "lot 48",
            "lot48a",
            "lot 48a",
        ],
        "Werblin Back Entrance": [
            "sonny",
            "werblin",
            "weblin",
            "webrlin",
            "wer",
            "web",
            "son",
        ],
        "Werblin Main Entrance": [],
        "Zimmerli Arts Museum": [
            "zim",
            "zimm",
            "zimmli",
            "zimmerli",
        ],
    },
    "merge": [
        ["Werblin Main Entrance", "Werblin Back Entrance"],
        ["Sciences Building", "Allison Road Classrooms"],
        ["Rockoff Hall", "Bravo Supermarket"],
    ],
}
